[
	{
		"value": "230100",
		"label": "哈尔滨市"
	},
	{
		"value": "230200",
		"label": "齐齐哈尔市"
	},
	{
		"value": "230300",
		"label": "鸡西市"
	},
	{
		"value": "230400",
		"label": "鹤岗市"
	},
	{
		"value": "230500",
		"label": "双鸭山市"
	},
	{
		"value": "230600",
		"label": "大庆市"
	},
	{
		"value": "230700",
		"label": "伊春市"
	},
	{
		"value": "230800",
		"label": "佳木斯市"
	},
	{
		"value": "230900",
		"label": "七台河市"
	},
	{
		"value": "231000",
		"label": "牡丹江市"
	},
	{
		"value": "231100",
		"label": "黑河市"
	},
	{
		"value": "231200",
		"label": "绥化市"
	},
	{
		"value": "232700",
		"label": "大兴安岭地区"
	}
]